HanLabImport/__init__.py
HanLabImport/io.py
HanLabImport/version.py
HanLabImport/config/HanLab.cfg
HanLabImport/config/__init__.py
HanLabImport/config/config.py
HanLabImport-0.1.1.dist-info/LICENSE
HanLabImport-0.1.1.dist-info/METADATA
HanLabImport-0.1.1.dist-info/WHEEL
HanLabImport-0.1.1.dist-info/top_level.txt
HanLabImport-0.1.1.dist-info/RECORD
