Metadata-Version: 2.1
Name: HanLabImport
Version: 0.1.1
Summary: Import tools for DNPLab specific to the Han Lab
Home-page: https://github.com/Bridge12Technologies/HanLabImport
Author: Thorsten Maly
Author-email: tmaly@bridge12.com
Project-URL: Tracker, https://github.com/Bridge12Technologies/HanLabImport/issues
Requires-Python: >=3.10
License-File: LICENSE
Requires-Dist: numpy (>=1.24)
